milliontrees/__init__.py
milliontrees/download_datasets.py
milliontrees/get_dataset.py
milliontrees/version.py
milliontrees/common/__init__.py
milliontrees/common/data_loaders.py
milliontrees/common/grouper.py
milliontrees/common/utils.py
milliontrees/common/metrics/__init__.py
milliontrees/common/metrics/all_metrics.py
milliontrees/common/metrics/loss.py
milliontrees/common/metrics/metric.py
milliontrees/datasets/TreeBoxes.py
milliontrees/datasets/TreePoints.py
milliontrees/datasets/TreePolygons.py
milliontrees/datasets/__init__.py
milliontrees/datasets/download_utils.py
milliontrees/datasets/milliontrees_dataset.py
milliontrees-0.5.0.dist-info/licenses/LICENSE
milliontrees-0.5.0.dist-info/METADATA
milliontrees-0.5.0.dist-info/WHEEL
milliontrees-0.5.0.dist-info/top_level.txt
milliontrees-0.5.0.dist-info/RECORD
