Metadata-Version: 2.4
Name: milliontrees
Version: 0.5.0
Summary: Benchmark dataset for Airborne Tree Machine Learning
Author-email: Ben Weinstein <benweinstein@weecology.org>, Henry Senyondo <henrykironde@gmail.com>, Ethan White <ethan@weecology.org>
License: MIT
Project-URL: Documentation, http://milliontrees.readthedocs.io/en/latest/
Project-URL: Source, https://github.com/Weecology/MillionTrees
Project-URL: Contributors, https://github.com/Weecology/MillionTrees/graphs/contributors
Classifier: Development Status :: 6 - Mature
Classifier: License :: OSI Approved :: MIT License
Classifier: Operating System :: MacOS
Classifier: Operating System :: Microsoft :: Windows
Classifier: Operating System :: POSIX
Classifier: Operating System :: Unix
Classifier: Programming Language :: Python :: 3 :: Only
Classifier: Programming Language :: Python :: 3.8
Classifier: Programming Language :: Python :: 3.9
Classifier: Programming Language :: Python :: 3.10
Classifier: Programming Language :: Python :: 3.11
Classifier: Programming Language :: Python :: 3.12
Classifier: Topic :: Scientific/Engineering :: Image Processing
Classifier: Topic :: Scientific/Engineering :: Image Recognition
Requires-Python: <3.13,>=3.10
License-File: LICENSE
Requires-Dist: numpy
Requires-Dist: pandas
Requires-Dist: pillow
Requires-Dist: torch
Requires-Dist: torchvision
Requires-Dist: tqdm
Requires-Dist: scikit-learn
Requires-Dist: shapely
Requires-Dist: torchmetrics
Requires-Dist: pyarrow>=17.0.0
Requires-Dist: datasets
Provides-Extra: dev
Requires-Dist: pytest; extra == "dev"
Requires-Dist: bumpversion; extra == "dev"
Requires-Dist: yapf; extra == "dev"
Requires-Dist: docformatter; extra == "dev"
Requires-Dist: black; extra == "dev"
Requires-Dist: flake8; extra == "dev"
Requires-Dist: label-studio-sdk; extra == "dev"
Requires-Dist: paramiko; extra == "dev"
Requires-Dist: python-dotenv; extra == "dev"
Requires-Dist: outdated; extra == "dev"
Requires-Dist: build; extra == "dev"
Requires-Dist: twine; extra == "dev"
Requires-Dist: deepforest; extra == "dev"
Requires-Dist: geopandas; extra == "dev"
Requires-Dist: rasterio; extra == "dev"
Requires-Dist: scikit-image; extra == "dev"
Requires-Dist: requests; extra == "dev"
Requires-Dist: neonutilities; extra == "dev"
Requires-Dist: dask[diagnostics]; extra == "dev"
Requires-Dist: transformers>=5.0.0rc1; extra == "dev"
Requires-Dist: accelerate; extra == "dev"
Requires-Dist: safetensors; extra == "dev"
Requires-Dist: huggingface-hub>=1.0.0; extra == "dev"
Requires-Dist: tokenizers>=0.20.0; extra == "dev"
Requires-Dist: matplotlib; extra == "dev"
Requires-Dist: opencv-python; extra == "dev"
Provides-Extra: docs
Requires-Dist: sphinx; extra == "docs"
Requires-Dist: furo; extra == "docs"
Requires-Dist: sphinx_markdown_tables; extra == "docs"
Requires-Dist: myst_parser; extra == "docs"
Requires-Dist: sphinx_rtd_theme; extra == "docs"
Requires-Dist: sphinx-design; extra == "docs"
Requires-Dist: nbmake; extra == "docs"
Requires-Dist: nbsphinx; extra == "docs"
Requires-Dist: nbqa; extra == "docs"
Dynamic: license-file
